Workbook

Sheet Setup
A1: Projects | B1: Categories | C1: Payment Modes | D1: Statuses
A2: Project A | B2: Material | C2: UPI | D2: Approved
A3: Project B | B3: Labour | C3: Bank Transfer | D3: Needs Review
A4: Project C | B4: Transport | C4: Cash | D4: Possible Duplicate
A5: General / Office | B5: Fuel | C5: Cheque | D5: Rejected
A6: Unassigned | B6: Machinery | C6: Card
B7: Contractor / Subcontractor | C7: Other
B8: Equipment
B9: Site Expense
B10: Office Expense
B11: Advance Payment
B12: Salary
B13: Food / Accommodation
B14: Other

Sheet All Payments
A1: Transaction ID | B1: Date | C1: Time | D1: Amount (₹) | E1: Paid To | F1: Project | G1: Category | H1: Purpose / Remark | I1: Payment Mode | J1: Bank / UPI App | K1: Reference No. | L1: Screenshot File | M1: AI Confidence % | N1: Status | O1: Duplicate Key
O5: =IF(OR(B5="",D5="",E5=""),"",TEXT(B5,"yyyymmdd")&"|"&TEXT(D5,"0.00")&"|"&LOWER(E5)&"|"&K5)
O6: =IF(OR(B6="",D6="",E6=""),"",TEXT(B6,"yyyymmdd")&"|"&TEXT(D6,"0.00")&"|"&LOWER(E6)&"|"&K6)
O7: =IF(OR(B7="",D7="",E7=""),"",TEXT(B7,"yyyymmdd")&"|"&TEXT(D7,"0.00")&"|"&LOWER(E7)&"|"&K7)
O8: =IF(OR(B8="",D8="",E8=""),"",TEXT(B8,"yyyymmdd")&"|"&TEXT(D8,"0.00")&"|"&LOWER(E8)&"|"&K8)
O9: =IF(OR(B9="",D9="",E9=""),"",TEXT(B9,"yyyymmdd")&"|"&TEXT(D9,"0.00")&"|"&LOWER(E9)&"|"&K9)
O10: =IF(OR(B10="",D10="",E10=""),"",TEXT(B10,"yyyymmdd")&"|"&TEXT(D10,"0.00")&"|"&LOWER(E10)&"|"&K10)
O11: =IF(OR(B11="",D11="",E11=""),"",TEXT(B11,"yyyymmdd")&"|"&TEXT(D11,"0.00")&"|"&LOWER(E11)&"|"&K11)
O12: =IF(OR(B12="",D12="",E12=""),"",TEXT(B12,"yyyymmdd")&"|"&TEXT(D12,"0.00")&"|"&LOWER(E12)&"|"&K12)
O13: =IF(OR(B13="",D13="",E13=""),"",TEXT(B13,"yyyymmdd")&"|"&TEXT(D13,"0.00")&"|"&LOWER(E13)&"|"&K13)
O14: =IF(OR(B14="",D14="",E14=""),"",TEXT(B14,"yyyymmdd")&"|"&TEXT(D14,"0.00")&"|"&LOWER(E14)&"|"&K14)
O15: =IF(OR(B15="",D15="",E15=""),"",TEXT(B15,"yyyymmdd")&"|"&TEXT(D15,"0.00")&"|"&LOWER(E15)&"|"&K15)
O16: =IF(OR(B16="",D16="",E16=""),"",TEXT(B16,"yyyymmdd")&"|"&TEXT(D16,"0.00")&"|"&LOWER(E16)&"|"&K16)
... O501: =IF(OR(B501="",D501="",E501=""),"",TEXT(B501,"yyyymmdd")&"|"&TEXT(D501,"0.00")&"|"&LOWER(E501)&"|"&K501)

Sheet Daily Summary
A1: Date | B1: No. of Payments | C1: Total Paid (₹)
A2: 46266 | B2: =COUNTIFS('All Payments'!$B$2:$B$501,A2,'All Payments'!$N$2:$N$501,"Approved") | C2: =SUMIFS('All Payments'!$D$2:$D$501,'All Payments'!$B$2:$B$501,A2,'All Payments'!$N$2:$N$501,"Approved")
A3: =A2+1 | B3: =COUNTIFS('All Payments'!$B$2:$B$501,A3,'All Payments'!$N$2:$N$501,"Approved") | C3: =SUMIFS('All Payments'!$D$2:$D$501,'All Payments'!$B$2:$B$501,A3,'All Payments'!$N$2:$N$501,"Approved")
A4: =A3+1 | B4: =COUNTIFS('All Payments'!$B$2:$B$501,A4,'All Payments'!$N$2:$N$501,"Approved") | C4: =SUMIFS('All Payments'!$D$2:$D$501,'All Payments'!$B$2:$B$501,A4,'All Payments'!$N$2:$N$501,"Approved")
A5: =A4+1 | B5: =COUNTIFS('All Payments'!$B$2:$B$501,A5,'All Payments'!$N$2:$N$501,"Approved") | C5: =SUMIFS('All Payments'!$D$2:$D$501,'All Payments'!$B$2:$B$501,A5,'All Payments'!$N$2:$N$501,"Approved")
A6: =A5+1 | B6: =COUNTIFS('All Payments'!$B$2:$B$501,A6,'All Payments'!$N$2:$N$501,"Approved") | C6: =SUMIFS('All Payments'!$D$2:$D$501,'All Payments'!$B$2:$B$501,A6,'All Payments'!$N$2:$N$501,"Approved")
A7: =A6+1 | B7: =COUNTIFS('All Payments'!$B$2:$B$501,A7,'All Payments'!$N$2:$N$501,"Approved") | C7: =SUMIFS('All Payments'!$D$2:$D$501,'All Payments'!$B$2:$B$501,A7,'All Payments'!$N$2:$N$501,"Approved")
A8: =A7+1 | B8: =COUNTIFS('All Payments'!$B$2:$B$501,A8,'All Payments'!$N$2:$N$501,"Approved") | C8: =SUMIFS('All Payments'!$D$2:$D$501,'All Payments'!$B$2:$B$501,A8,'All Payments'!$N$2:$N$501,"Approved")
A9: =A8+1 | B9: =COUNTIFS('All Payments'!$B$2:$B$501,A9,'All Payments'!$N$2:$N$501,"Approved") | C9: =SUMIFS('All Payments'!$D$2:$D$501,'All Payments'!$B$2:$B$501,A9,'All Payments'!$N$2:$N$501,"Approved")
A10: =A9+1 | B10: =COUNTIFS('All Payments'!$B$2:$B$501,A10,'All Payments'!$N$2:$N$501,"Approved") | C10: =SUMIFS('All Payments'!$D$2:$D$501,'All Payments'!$B$2:$B$501,A10,'All Payments'!$N$2:$N$501,"Approved")
A11: =A10+1 | B11: =COUNTIFS('All Payments'!$B$2:$B$501,A11,'All Payments'!$N$2:$N$501,"Approved") | C11: =SUMIFS('All Payments'!$D$2:$D$501,'All Payments'!$B$2:$B$501,A11,'All Payments'!$N$2:$N$501,"Approved")
A12: =A11+1 | B12: =COUNTIFS('All Payments'!$B$2:$B$501,A12,'All Payments'!$N$2:$N$501,"Approved") | C12: =SUMIFS('All Payments'!$D$2:$D$501,'All Payments'!$B$2:$B$501,A12,'All Payments'!$N$2:$N$501,"Approved")
A13: =A12+1 | B13: =COUNTIFS('All Payments'!$B$2:$B$501,A13,'All Payments'!$N$2:$N$501,"Approved") | C13: =SUMIFS('All Payments'!$D$2:$D$501,'All Payments'!$B$2:$B$501,A13,'All Payments'!$N$2:$N$501,"Approved")
A14: =A13+1 | B14: =COUNTIFS('All Payments'!$B$2:$B$501,A14,'All Payments'!$N$2:$N$501,"Approved") | C14: =SUMIFS('All Payments'!$D$2:$D$501,'All Payments'!$B$2:$B$501,A14,'All Payments'!$N$2:$N$501,"Approved")
... A367: =A366+1 | B367: =COUNTIFS('All Payments'!$B$2:$B$501,A367,'All Payments'!$N$2:$N$501,"Approved") | C367: =SUMIFS('All Payments'!$D$2:$D$501,'All Payments'!$B$2:$B$501,A367,'All Payments'!$N$2:$N$501,"Approved")

Sheet Monthly Summary
A1: Month | B1: No. of Payments | C1: Total Paid (₹)
A2: 46023 | B2: =COUNTIFS('All Payments'!$B$2:$B$501,">="&A2,'All Payments'!$B$2:$B$501,"<"&EDATE(A2,1),'All Payments'!$N$2:$N$501,"Approved") | C2: =SUMIFS('All Payments'!$D$2:$D$501,'All Payments'!$B$2:$B$501,">="&A2,'All Payments'!$B$2:$B$501,"<"&EDATE(A2,1),'All Payments'!$N$2:$N$501,"Approved")
A3: 46054 | B3: =COUNTIFS('All Payments'!$B$2:$B$501,">="&A3,'All Payments'!$B$2:$B$501,"<"&EDATE(A3,1),'All Payments'!$N$2:$N$501,"Approved") | C3: =SUMIFS('All Payments'!$D$2:$D$501,'All Payments'!$B$2:$B$501,">="&A3,'All Payments'!$B$2:$B$501,"<"&EDATE(A3,1),'All Payments'!$N$2:$N$501,"Approved")
A4: 46082 | B4: =COUNTIFS('All Payments'!$B$2:$B$501,">="&A4,'All Payments'!$B$2:$B$501,"<"&EDATE(A4,1),'All Payments'!$N$2:$N$501,"Approved") | C4: =SUMIFS('All Payments'!$D$2:$D$501,'All Payments'!$B$2:$B$501,">="&A4,'All Payments'!$B$2:$B$501,"<"&EDATE(A4,1),'All Payments'!$N$2:$N$501,"Approved")
A5: 46113 | B5: =COUNTIFS('All Payments'!$B$2:$B$501,">="&A5,'All Payments'!$B$2:$B$501,"<"&EDATE(A5,1),'All Payments'!$N$2:$N$501,"Approved") | C5: =SUMIFS('All Payments'!$D$2:$D$501,'All Payments'!$B$2:$B$501,">="&A5,'All Payments'!$B$2:$B$501,"<"&EDATE(A5,1),'All Payments'!$N$2:$N$501,"Approved")
A6: 46143 | B6: =COUNTIFS('All Payments'!$B$2:$B$501,">="&A6,'All Payments'!$B$2:$B$501,"<"&EDATE(A6,1),'All Payments'!$N$2:$N$501,"Approved") | C6: =SUMIFS('All Payments'!$D$2:$D$501,'All Payments'!$B$2:$B$501,">="&A6,'All Payments'!$B$2:$B$501,"<"&EDATE(A6,1),'All Payments'!$N$2:$N$501,"Approved")
A7: 46174 | B7: =COUNTIFS('All Payments'!$B$2:$B$501,">="&A7,'All Payments'!$B$2:$B$501,"<"&EDATE(A7,1),'All Payments'!$N$2:$N$501,"Approved") | C7: =SUMIFS('All Payments'!$D$2:$D$501,'All Payments'!$B$2:$B$501,">="&A7,'All Payments'!$B$2:$B$501,"<"&EDATE(A7,1),'All Payments'!$N$2:$N$501,"Approved")
A8: 46204 | B8: =COUNTIFS('All Payments'!$B$2:$B$501,">="&A8,'All Payments'!$B$2:$B$501,"<"&EDATE(A8,1),'All Payments'!$N$2:$N$501,"Approved") | C8: =SUMIFS('All Payments'!$D$2:$D$501,'All Payments'!$B$2:$B$501,">="&A8,'All Payments'!$B$2:$B$501,"<"&EDATE(A8,1),'All Payments'!$N$2:$N$501,"Approved")
A9: 46235 | B9: =COUNTIFS('All Payments'!$B$2:$B$501,">="&A9,'All Payments'!$B$2:$B$501,"<"&EDATE(A9,1),'All Payments'!$N$2:$N$501,"Approved") | C9: =SUMIFS('All Payments'!$D$2:$D$501,'All Payments'!$B$2:$B$501,">="&A9,'All Payments'!$B$2:$B$501,"<"&EDATE(A9,1),'All Payments'!$N$2:$N$501,"Approved")
A10: 46266 | B10: =COUNTIFS('All Payments'!$B$2:$B$501,">="&A10,'All Payments'!$B$2:$B$501,"<"&EDATE(A10,1),'All Payments'!$N$2:$N$501,"Approved") | C10: =SUMIFS('All Payments'!$D$2:$D$501,'All Payments'!$B$2:$B$501,">="&A10,'All Payments'!$B$2:$B$501,"<"&EDATE(A10,1),'All Payments'!$N$2:$N$501,"Approved")
A11: 46296 | B11: =COUNTIFS('All Payments'!$B$2:$B$501,">="&A11,'All Payments'!$B$2:$B$501,"<"&EDATE(A11,1),'All Payments'!$N$2:$N$501,"Approved") | C11: =SUMIFS('All Payments'!$D$2:$D$501,'All Payments'!$B$2:$B$501,">="&A11,'All Payments'!$B$2:$B$501,"<"&EDATE(A11,1),'All Payments'!$N$2:$N$501,"Approved")
A12: 46327 | B12: =COUNTIFS('All Payments'!$B$2:$B$501,">="&A12,'All Payments'!$B$2:$B$501,"<"&EDATE(A12,1),'All Payments'!$N$2:$N$501,"Approved") | C12: =SUMIFS('All Payments'!$D$2:$D$501,'All Payments'!$B$2:$B$501,">="&A12,'All Payments'!$B$2:$B$501,"<"&EDATE(A12,1),'All Payments'!$N$2:$N$501,"Approved")
A13: 46357 | B13: =COUNTIFS('All Payments'!$B$2:$B$501,">="&A13,'All Payments'!$B$2:$B$501,"<"&EDATE(A13,1),'All Payments'!$N$2:$N$501,"Approved") | C13: =SUMIFS('All Payments'!$D$2:$D$501,'All Payments'!$B$2:$B$501,">="&A13,'All Payments'!$B$2:$B$501,"<"&EDATE(A13,1),'All Payments'!$N$2:$N$501,"Approved")

Sheet Project Summary
A1: Project | B1: No. of Payments | C1: Total Paid (₹) | D1: % of Total
A2: Project A | B2: =COUNTIFS('All Payments'!$F$2:$F$501,A2,'All Payments'!$N$2:$N$501,"Approved") | C2: =SUMIFS('All Payments'!$D$2:$D$501,'All Payments'!$F$2:$F$501,A2,'All Payments'!$N$2:$N$501,"Approved") | D2: =IFERROR(C2/SUM($C$2:$C$6),0)
A3: Project B | B3: =COUNTIFS('All Payments'!$F$2:$F$501,A3,'All Payments'!$N$2:$N$501,"Approved") | C3: =SUMIFS('All Payments'!$D$2:$D$501,'All Payments'!$F$2:$F$501,A3,'All Payments'!$N$2:$N$501,"Approved") | D3: =IFERROR(C3/SUM($C$2:$C$6),0)
A4: Project C | B4: =COUNTIFS('All Payments'!$F$2:$F$501,A4,'All Payments'!$N$2:$N$501,"Approved") | C4: =SUMIFS('All Payments'!$D$2:$D$501,'All Payments'!$F$2:$F$501,A4,'All Payments'!$N$2:$N$501,"Approved") | D4: =IFERROR(C4/SUM($C$2:$C$6),0)
A5: General / Office | B5: =COUNTIFS('All Payments'!$F$2:$F$501,A5,'All Payments'!$N$2:$N$501,"Approved") | C5: =SUMIFS('All Payments'!$D$2:$D$501,'All Payments'!$F$2:$F$501,A5,'All Payments'!$N$2:$N$501,"Approved") | D5: =IFERROR(C5/SUM($C$2:$C$6),0)
A6: Unassigned | B6: =COUNTIFS('All Payments'!$F$2:$F$501,A6,'All Payments'!$N$2:$N$501,"Approved") | C6: =SUMIFS('All Payments'!$D$2:$D$501,'All Payments'!$F$2:$F$501,A6,'All Payments'!$N$2:$N$501,"Approved") | D6: =IFERROR(C6/SUM($C$2:$C$6),0)

Sheet Category Summary
A1: Category | B1: No. of Payments | C1: Total Paid (₹)
A2: Material | B2: =COUNTIFS('All Payments'!$G$2:$G$501,A2,'All Payments'!$N$2:$N$501,"Approved") | C2: =SUMIFS('All Payments'!$D$2:$D$501,'All Payments'!$G$2:$G$501,A2,'All Payments'!$N$2:$N$501,"Approved")
A3: Labour | B3: =COUNTIFS('All Payments'!$G$2:$G$501,A3,'All Payments'!$N$2:$N$501,"Approved") | C3: =SUMIFS('All Payments'!$D$2:$D$501,'All Payments'!$G$2:$G$501,A3,'All Payments'!$N$2:$N$501,"Approved")
A4: Transport | B4: =COUNTIFS('All Payments'!$G$2:$G$501,A4,'All Payments'!$N$2:$N$501,"Approved") | C4: =SUMIFS('All Payments'!$D$2:$D$501,'All Payments'!$G$2:$G$501,A4,'All Payments'!$N$2:$N$501,"Approved")
A5: Fuel | B5: =COUNTIFS('All Payments'!$G$2:$G$501,A5,'All Payments'!$N$2:$N$501,"Approved") | C5: =SUMIFS('All Payments'!$D$2:$D$501,'All Payments'!$G$2:$G$501,A5,'All Payments'!$N$2:$N$501,"Approved")
A6: Machinery | B6: =COUNTIFS('All Payments'!$G$2:$G$501,A6,'All Payments'!$N$2:$N$501,"Approved") | C6: =SUMIFS('All Payments'!$D$2:$D$501,'All Payments'!$G$2:$G$501,A6,'All Payments'!$N$2:$N$501,"Approved")
A7: Contractor / Subcontractor | B7: =COUNTIFS('All Payments'!$G$2:$G$501,A7,'All Payments'!$N$2:$N$501,"Approved") | C7: =SUMIFS('All Payments'!$D$2:$D$501,'All Payments'!$G$2:$G$501,A7,'All Payments'!$N$2:$N$501,"Approved")
A8: Equipment | B8: =COUNTIFS('All Payments'!$G$2:$G$501,A8,'All Payments'!$N$2:$N$501,"Approved") | C8: =SUMIFS('All Payments'!$D$2:$D$501,'All Payments'!$G$2:$G$501,A8,'All Payments'!$N$2:$N$501,"Approved")
A9: Site Expense | B9: =COUNTIFS('All Payments'!$G$2:$G$501,A9,'All Payments'!$N$2:$N$501,"Approved") | C9: =SUMIFS('All Payments'!$D$2:$D$501,'All Payments'!$G$2:$G$501,A9,'All Payments'!$N$2:$N$501,"Approved")
A10: Office Expense | B10: =COUNTIFS('All Payments'!$G$2:$G$501,A10,'All Payments'!$N$2:$N$501,"Approved") | C10: =SUMIFS('All Payments'!$D$2:$D$501,'All Payments'!$G$2:$G$501,A10,'All Payments'!$N$2:$N$501,"Approved")
A11: Advance Payment | B11: =COUNTIFS('All Payments'!$G$2:$G$501,A11,'All Payments'!$N$2:$N$501,"Approved") | C11: =SUMIFS('All Payments'!$D$2:$D$501,'All Payments'!$G$2:$G$501,A11,'All Payments'!$N$2:$N$501,"Approved")
A12: Salary | B12: =COUNTIFS('All Payments'!$G$2:$G$501,A12,'All Payments'!$N$2:$N$501,"Approved") | C12: =SUMIFS('All Payments'!$D$2:$D$501,'All Payments'!$G$2:$G$501,A12,'All Payments'!$N$2:$N$501,"Approved")
A13: Food / Accommodation | B13: =COUNTIFS('All Payments'!$G$2:$G$501,A13,'All Payments'!$N$2:$N$501,"Approved") | C13: =SUMIFS('All Payments'!$D$2:$D$501,'All Payments'!$G$2:$G$501,A13,'All Payments'!$N$2:$N$501,"Approved")
A14: Other | B14: =COUNTIFS('All Payments'!$G$2:$G$501,A14,'All Payments'!$N$2:$N$501,"Approved") | C14: =SUMIFS('All Payments'!$D$2:$D$501,'All Payments'!$G$2:$G$501,A14,'All Payments'!$N$2:$N$501,"Approved")

Sheet Needs Review
A1: Transaction ID | B1: Date | C1: Amount (₹) | D1: Paid To | E1: Detected Project | F1: Detected Category | G1: Reason for Review | H1: Final Decision

Sheet Dashboard
A1: GCGW PAYMENT MANAGEMENT DASHBOARD
A4: Metric | B4: Value | D4: Project | E4: Payments | F4: Total Paid (₹)
A5: Total Approved Payments | B5: =COUNTIF('All Payments'!$N$2:$N$501,"Approved") | D5: Project A | E5: =COUNTIFS('All Payments'!$F$2:$F$501,D5,'All Payments'!$N$2:$N$501,"Approved") | F5: =SUMIFS('All Payments'!$D$2:$D$501,'All Payments'!$F$2:$F$501,D5,'All Payments'!$N$2:$N$501,"Approved")
A6: Total Amount Paid | B6: =SUMIFS('All Payments'!$D$2:$D$501,'All Payments'!$N$2:$N$501,"Approved") | D6: Project B | E6: =COUNTIFS('All Payments'!$F$2:$F$501,D6,'All Payments'!$N$2:$N$501,"Approved") | F6: =SUMIFS('All Payments'!$D$2:$D$501,'All Payments'!$F$2:$F$501,D6,'All Payments'!$N$2:$N$501,"Approved")
A7: This Month Paid | B7: =SUMIFS('All Payments'!$D$2:$D$501,'All Payments'!$B$2:$B$501,">="&EOMONTH(TODAY(),-1)+1,'All Payments'!$B$2:$B$501,"<="&EOMONTH(TODAY(),0),'All Payments'!$N$2:$N$501,"Approved") | D7: Project C | E7: =COUNTIFS('All Payments'!$F$2:$F$501,D7,'All Payments'!$N$2:$N$501,"Approved") | F7: =SUMIFS('All Payments'!$D$2:$D$501,'All Payments'!$F$2:$F$501,D7,'All Payments'!$N$2:$N$501,"Approved")
A8: Today Paid | B8: =SUMIFS('All Payments'!$D$2:$D$501,'All Payments'!$B$2:$B$501,TODAY(),'All Payments'!$N$2:$N$501,"Approved") | D8: General / Office | E8: =COUNTIFS('All Payments'!$F$2:$F$501,D8,'All Payments'!$N$2:$N$501,"Approved") | F8: =SUMIFS('All Payments'!$D$2:$D$501,'All Payments'!$F$2:$F$501,D8,'All Payments'!$N$2:$N$501,"Approved")
A9: Needs Review | B9: =COUNTIF('All Payments'!$N$2:$N$501,"Needs Review") | D9: Unassigned | E9: =COUNTIFS('All Payments'!$F$2:$F$501,D9,'All Payments'!$N$2:$N$501,"Approved") | F9: =SUMIFS('All Payments'!$D$2:$D$501,'All Payments'!$F$2:$F$501,D9,'All Payments'!$N$2:$N$501,"Approved")
A10: Possible Duplicates | B10: =COUNTIF('All Payments'!$N$2:$N$501,"Possible Duplicate")
A31: Agent-ready workbook: future screenshot-processing code should append each approved transaction to 'All Payments'. Daily, monthly, project, category and dashboard totals will update automatically.
